argon2/low_level.py
argon2/_legacy.py
argon2/_utils.py
argon2/_ffi_build.py
argon2/_password_hasher.py
argon2/_ffi.abi3.so
argon2/__init__.py
argon2/exceptions.py
argon2/__main__.py
argon2_cffi-21.1.0.dist-info/AUTHORS.rst
argon2_cffi-21.1.0.dist-info/top_level.txt
argon2_cffi-21.1.0.dist-info/METADATA
argon2_cffi-21.1.0.dist-info/RECORD
argon2_cffi-21.1.0.dist-info/LICENSE
argon2_cffi-21.1.0.dist-info/WHEEL
